baseplate_celery/__init__.py
baseplate_celery/py.typed
baseplate_celery-1.0.0a1.dist-info/LICENSE
baseplate_celery-1.0.0a1.dist-info/METADATA
baseplate_celery-1.0.0a1.dist-info/WHEEL
baseplate_celery-1.0.0a1.dist-info/top_level.txt
baseplate_celery-1.0.0a1.dist-info/zip-safe
baseplate_celery-1.0.0a1.dist-info/RECORD
