Metadata-Version: 2.1
Name: baseplate-celery
Version: 1.0.0a1
Summary: reddit's python celery framework
Home-page: https://github.com/reddit/baseplate-celery
Author: reddit
License: BSD
Project-URL: Documentation, https://reddit-baseplate-celery.readthedocs.io/
Platform: UNKNOWN
Classifier: Development Status :: 5 - Production/Stable
Classifier: License :: OSI Approved :: BSD License
Classifier: Programming Language :: Python
Classifier: Programming Language :: Python :: 3.7
Classifier: Programming Language :: Python :: 3.8
Classifier: Programming Language :: Python :: 3.9
Classifier: Topic :: Software Development :: Libraries
Requires-Python: >=3.7
Requires-Dist: baseplate (<3.0,>=2.0.0a1)
